llm_multi/__init__.py
llm_multi/archive.py
llm_multi/cli.py
llm_multi/format.py
llm_multi/map.py
llm_multi-0.1.0.dist-info/WHEEL
llm_multi-0.1.0.dist-info/entry_points.txt
llm_multi-0.1.0.dist-info/METADATA
llm_multi-0.1.0.dist-info/RECORD
