Metadata-Version: 2.3
Name: llm-multi
Version: 0.1.0
Summary: A plugin for LLM that combines file bundling and LLM mapping capabilities
Requires-Dist: llm>=0.26
Requires-Python: >=3.12
